shdo.py
shdo/shdo.py
shdo-0.1.3.dist-info/METADATA
shdo-0.1.3.dist-info/WHEEL
shdo-0.1.3.dist-info/entry_points.txt
shdo-0.1.3.dist-info/top_level.txt
shdo-0.1.3.dist-info/RECORD
