Metadata-Version: 2.4
Name: shdo
Version: 0.1.3
Summary: A tool to escalate privileges in Android
Home-page: https://github.com/42zen/shdo
Author: Mathias Bochet (aka Zen)
Dynamic: author
Dynamic: description
Dynamic: home-page
Dynamic: summary
